cuba_weather_insmet/__init__.py
cuba_weather_insmet/insmet_webparser/__init__.py
cuba_weather_insmet/repositories/__init__.py
cuba_weather_insmet/repositories/source_repository.py
cuba_weather_insmet/repositories/weather_repository.py
cuba_weather_insmet-0.0.1.dist-info/LICENSE
cuba_weather_insmet-0.0.1.dist-info/METADATA
cuba_weather_insmet-0.0.1.dist-info/WHEEL
cuba_weather_insmet-0.0.1.dist-info/top_level.txt
cuba_weather_insmet-0.0.1.dist-info/RECORD
